libcurses/__init__.py
libcurses/border.py
libcurses/bw.py
libcurses/colormap.py
libcurses/core.py
libcurses/getkey.py
libcurses/getline.py
libcurses/grid.py
libcurses/logsink.py
libcurses/menu.py
libcurses/mouse.py
libcurses/mouseevent.py
libcurses/py.typed
libcurses/stack.py
rlane_libcurses-1.0.9.dist-info/METADATA
rlane_libcurses-1.0.9.dist-info/WHEEL
rlane_libcurses-1.0.9.dist-info/entry_points.txt
rlane_libcurses-1.0.9.dist-info/licenses/LICENSE
rlane_libcurses-1.0.9.dist-info/RECORD
