Metadata-Version: 2.1
Name: rlane-libcurses
Version: 1.0.9
Summary: Curses based boxes, menus, loggers
Keywords: curses,python,xterm-256color,mouse
Author-Email: Russel Lane <russel@rlane.com>
License: MIT
Classifier: Development Status :: 4 - Beta
Classifier: Environment :: Console :: Curses
Classifier: Intended Audience :: Developers
Classifier: License :: OSI Approved :: MIT License
Classifier: Programming Language :: Python :: 3
Classifier: Topic :: Software Development :: Libraries :: Python Modules
Project-URL: Homepage, https://github.com/russellane/libcurses
Requires-Python: >=3.10
Requires-Dist: loguru>=0.7.2
